test_projectsss/ObjectDetection.py
test_projectsss/__init__.py
test_projectsss-0.0.1.dist-info/LICENSE
test_projectsss-0.0.1.dist-info/METADATA
test_projectsss-0.0.1.dist-info/WHEEL
test_projectsss-0.0.1.dist-info/top_level.txt
test_projectsss-0.0.1.dist-info/RECORD
